statannotations/Annotation.py
statannotations/Annotator.py
statannotations/PValueFormat.py
statannotations/_GroupsPositions.py
statannotations/_Plotter.py
statannotations/_Xpositions.py
statannotations/__init__.py
statannotations/_version.py
statannotations/compat.py
statannotations/format_annotations.py
statannotations/utils.py
statannotations/stats/ComparisonsCorrection.py
statannotations/stats/StatResult.py
statannotations/stats/StatTest.py
statannotations/stats/__init__.py
statannotations/stats/test.py
statannotations/stats/tests.py
statannotations/stats/utils.py
statannotations-0.7.2.dist-info/LICENSE
statannotations-0.7.2.dist-info/METADATA
statannotations-0.7.2.dist-info/WHEEL
statannotations-0.7.2.dist-info/top_level.txt
statannotations-0.7.2.dist-info/RECORD
