Metadata-Version: 2.1
Name: statannotations
Version: 0.7.2
Summary: add statistical significance or custom annotations on seaborn plots. Based on statannot 0.2.3
Home-page: https://github.com/trevismd/statannotations
Maintainer: Florian Charlier
Maintainer-email: trevis@cascliniques.be
License: MIT License
Classifier: Programming Language :: Python :: 3
Classifier: License :: OSI Approved :: MIT License
Classifier: Operating System :: OS Independent
Requires-Python: >=3.8
License-File: LICENSE
Requires-Dist: numpy>=1.12.1
Requires-Dist: seaborn>=0.9.0
Requires-Dist: matplotlib>=2.2.2
Requires-Dist: pandas>=0.23.0
Requires-Dist: scipy>=1.1.0
